{
  "sections": {
    "section_divider_WfYLrb": {
      "type": "section-divider",
      "settings": {
        "show_line": true,
        "width": "wrapper--full",
        "color_scheme": "",
        "padding_top": 0,
        "padding_bottom": 0
      }
    },
    "main": {
      "type": "product",
      "blocks": {
        "badges_EKgDG3": {
          "type": "badges",
          "settings": {
            "sale_badge": true,
            "product_badges": true,
            "custom_badge_1": "",
            "custom_badge_2": "",
            "custom_badge_3": "",
            "badge_border_style": "square",
            "padding_bottom": 8
          }
        },
        "title": {
          "type": "title",
          "settings": {
            "subheading_option": "breadcrumb",
            "heading_font_size": "heading-medium",
            "padding_bottom": 8
          }
        },
        "junip_junip_product_summary_3xhXcQ": {
          "type": "shopify://apps/junip/blocks/junip-product-summary/dc14f5a8-ed15-41b1-ad08-cfba23f9789b",
          "settings": {
            "product": "{{product}}",
            "alignment": ""
          }
        },
        "price": {
          "type": "price",
          "settings": {
            "text_font_size": "body-x-large",
            "show_shipping_policy": true,
            "padding_bottom": 8
          }
        },
        "siblings_RdbAxK": {
          "type": "siblings",
          "settings": {
            "siblings_collection": "",
            "sibling_color": "",
            "option_font_size": "body-medium",
            "value_font_size": "body-x-small",
            "padding_bottom": 16
          }
        },
        "variants": {
          "type": "variants",
          "settings": {
            "info_page": "ring-size-guide",
            "size_chart_style": "question",
            "option_font_size": "body-medium",
            "value_font_size": "body-x-small",
            "padding_bottom": 16
          }
        },
        "accordion_i6tbbM": {
          "type": "accordion",
          "settings": {
            "style": "collapsible",
            "show_description": true,
            "show_read_more": true,
            "default_open": false,
            "heading": "Description",
            "heading_font_size": "body-medium",
            "text": "",
            "text_font_size": "body-medium",
            "show_icon": false,
            "icon_name": "icon-award",
            "icon_size": 20,
            "icon_color": "",
            "padding_bottom": 8
          }
        },
        "hulk_product_options_product_customizer_c3X9gN": {
          "type": "shopify://apps/hulk-product-options/blocks/product_customizer/380168ef-9475-4244-a291-f66b189208b5",
          "settings": {
            "image_upload": true,
            "text_content": true,
            "text_color": true,
            "text_size": true,
            "font_picker": false,
            "save_image_content": "Save",
            "remove_elements": "Reset",
            "button_background_color": "#000000",
            "button_font_color": "#ffffff",
            "button_font_size": 18,
            "button_border": 1,
            "button_radius": 24,
            "border_color": "#000000",
            "image_class": "",
            "customize_image_properties": "Preview Image",
            "customize_logo_properties": "Uploaded Image",
            "text_content_properties": "Custom Text",
            "text_content_color_properties": "Custom Text Color",
            "text_content_size_properties": "Custom Text Size",
            "text_content_font_properties": "Custom Text Font",
            "multiple_image_class": ""
          }
        },
        "inventory_countdown_9EACqM": {
          "type": "inventory_countdown",
          "settings": {
            "show_notice": "always",
            "max_inventory": 10,
            "show_inventory_counter": false,
            "icon_size": 20,
            "in_stock_color": "#56ad6a",
            "low_stock_color": "#f79554",
            "out_of_stock_color": "#721c24",
            "padding_bottom": 24
          }
        },
        "buttons": {
          "type": "buttons",
          "settings": {
            "show_quantity": true,
            "button_type": "btn--black",
            "button_size": "btn--large",
            "button_style": "btn--solid",
            "show_dynamic_checkout": false,
            "button_type_dynamic": "btn--secondary",
            "button_size_dynamic": "btn--large",
            "button_style_dynamic": "btn--outline",
            "show_gift_card_recipient": false,
            "padding_bottom": 32
          }
        },
        "pickup": {
          "type": "pickup",
          "disabled": true,
          "settings": {
            "padding_bottom": 32
          }
        },
        "icon_2": {
          "type": "icon",
          "disabled": true,
          "settings": {
            "icon_name": "icon-recycle",
            "icon_size": 20,
            "icon_color": "",
            "text": "<p>Free 30 Days Returns</p>",
            "text_font_size": "body-small",
            "width": "full",
            "padding_bottom": 8
          }
        },
        "icon_1": {
          "type": "icon",
          "settings": {
            "icon_name": "icon-truck",
            "icon_size": 20,
            "icon_color": "",
            "text": "<p>PAWD provides free standard shipping</p>",
            "text_font_size": "body-small",
            "width": "full",
            "padding_bottom": 8
          }
        },
        "icon_bH3jWT": {
          "type": "icon",
          "disabled": true,
          "settings": {
            "icon_name": "icon-donation",
            "icon_size": 20,
            "icon_color": "",
            "text": "<p>1 year warranty</p>",
            "text_font_size": "body-small",
            "width": "full",
            "padding_bottom": 8
          }
        },
        "icon_c6KeCK": {
          "type": "icon",
          "disabled": true,
          "settings": {
            "icon_name": "icon-flare",
            "icon_size": 20,
            "icon_color": "",
            "text": "<p>14k Solid Gold</p>",
            "text_font_size": "body-small",
            "width": "full",
            "padding_bottom": 16
          }
        },
        "afterpay_on_site_messaging_payments_messaging_GQNKcn": {
          "type": "shopify://apps/afterpay-on-site-messaging/blocks/payments-messaging/f45a5524-d177-4475-bf59-281efd2215a8",
          "settings": {
            "text_align": "inherit",
            "margin_top": 16,
            "margin_bottom": 16,
            "color": "",
            "size": "md",
            "intro_text": "or",
            "show_interest_free": true,
            "payment_amount_is_bold": true,
            "show_with": true,
            "logo_type": "badge",
            "logo_theme": "black-on-mint",
            "modal_link_style": "circled-info-icon",
            "modal_theme": "mint",
            "breakpoint": 749,
            "text_align_mobile": "inherit",
            "margin_top_mobile": 16,
            "margin_bottom_mobile": 16,
            "show_lower_limit": true,
            "show_upper_limit": true,
            "show_if_outside_limits": true,
            "product": "{{product}}"
          }
        },
        "divider_RHQKMP": {
          "type": "divider",
          "disabled": true,
          "settings": {
            "show_line": true,
            "padding_bottom": 20
          }
        },
        "upsell": {
          "type": "upsell",
          "disabled": true,
          "settings": {
            "upsell_product": "",
            "upsell_product_list": [],
            "show_available_upsell_only": false,
            "layout": "stacked",
            "autoplay": false,
            "autoplay_speed": 8,
            "bg_color": "",
            "padding_bottom": 24
          }
        },
        "divider_1": {
          "type": "divider",
          "disabled": true,
          "settings": {
            "show_line": true,
            "padding_bottom": 16
          }
        },
        "features_chGfmk": {
          "type": "features",
          "disabled": true,
          "settings": {
            "icon_name": "icon-chat",
            "icon_size": 20,
            "title": "Need styling help?",
            "text_font_size": "body-medium",
            "text": "<p>Book an appointment with our virtual stylists! <a href=\"https://broadcast-theme-main.myshopify.com/pages/contact\" title=\"https://broadcast-theme-main.myshopify.com/pages/contact\">Chat now</a></p>",
            "bg_color": "#fcfbf9",
            "color": "",
            "padding_bottom": 16
          }
        }
      },
      "block_order": [
        "badges_EKgDG3",
        "title",
        "junip_junip_product_summary_3xhXcQ",
        "price",
        "siblings_RdbAxK",
        "variants",
        "accordion_i6tbbM",
        "hulk_product_options_product_customizer_c3X9gN",
        "inventory_countdown_9EACqM",
        "buttons",
        "pickup",
        "icon_2",
        "icon_1",
        "icon_bH3jWT",
        "icon_c6KeCK",
        "afterpay_on_site_messaging_payments_messaging_GQNKcn",
        "divider_RHQKMP",
        "upsell",
        "divider_1",
        "features_chGfmk"
      ],
      "settings": {
        "product_sticky_enable": true,
        "variant_image_scroll": true,
        "show_cart_bar": true,
        "enable_zoom": true,
        "enable_video_looping": false,
        "image_layout": "thumbnails-left",
        "image_size": "normal",
        "mobile_image_style": "thumbs",
        "color_scheme": "scheme-8a8a0884-d182-4e82-9721-b5dd023210e6",
        "padding_top": 40,
        "padding_bottom": 80
      }
    },
    "section_accordion_NMDgJD": {
      "type": "section-accordion",
      "blocks": {
        "image_VxNBFm": {
          "type": "image",
          "disabled": true,
          "settings": {
            "title": "How to Measure",
            "heading_font_size": "heading-small",
            "text": "<p>Measure around the widest part of your dog's neck, where the collar sits. Keep the tape snug but not tight. Add 2cm for comfort.</p>",
            "aspect_ratio": 0.6
          }
        },
        "image_xJkNDa": {
          "type": "image",
          "settings": {
            "title": "Measurement Diagram",
            "heading_font_size": "heading-small",
            "text": "<p>Measure around the widest part of your dog's neck, where the collar sits. Keep the tape snug but not tight. Add 2cm for comfort.</p>",
            "image": "shopify://shop_images/WhatsApp_Image_2026-03-18_at_11.12.02_AM.jpg",
            "aspect_ratio": 0.6
          }
        },
        "code_34JcTk": {
          "type": "code",
          "settings": {
            "code": "<table><thead><tr><th>Size</th><th>Neck Circumference</th></tr></thead><tbody><tr><td>XS</td><td>20\u201328 cm</td></tr><tr><td>S</td><td>28\u201336 cm</td></tr><tr><td>M</td><td>36\u201344 cm</td></tr><tr><td>L</td><td>44\u201352 cm</td></tr><tr><td>XL</td><td>52\u201360 cm</td></tr></tbody></table><p><em>Add 2cm for comfort.</em></p>"
          }
        }
      },
      "block_order": [
        "image_VxNBFm",
        "image_xJkNDa",
        "code_34JcTk"
      ],
      "name": "Accordion",
      "settings": {
        "default_open": false,
        "title": "Size guide",
        "heading_font_size": "heading-x-small",
        "show_icon": true,
        "icon_name": "icon-award",
        "icon_size": 20,
        "width": "wrapper",
        "color_scheme": "scheme-8a8a0884-d182-4e82-9721-b5dd023210e6",
        "icon_color": "",
        "padding_top": 0,
        "padding_bottom": 0
      }
    },
    "section_hero_Cz9YYe": {
      "type": "section-hero",
      "settings": {
        "image_1": "",
        "link": "",
        "width": "wrapper--full",
        "height": "screen-height-two-thirds",
        "flex_align_desktop": "align--middle-center-desktop",
        "content_width": 50,
        "mobile_height": "screen-height-three-quarters--mobile",
        "flex_align_mobile": "align--middle-center-mobile",
        "color_scheme": "scheme-8a8a0884-d182-4e82-9721-b5dd023210e6",
        "show_text_background": false,
        "overlay_type": "disabled",
        "padding_top": 20,
        "padding_bottom": 20,
        "show_placeholder": true
      }
    },
    "section_double_7bAatG": {
      "type": "section-double",
      "blocks": {
        "heading_KfRRxy": {
          "type": "heading",
          "settings": {
            "title": "Leather that earns its patina.",
            "heading_font_size": "heading-large",
            "padding_bottom": 16,
            "heading_tag": "automatic"
          }
        },
        "text_yFYiAe": {
          "type": "text",
          "settings": {
            "text": "<p>Full-grain leather, sourced and finished to age beautifully. No coating. No shortcuts. Just leather that softens with every walk and tells the story of your dog's life.</p>",
            "text_font_size": "body-medium",
            "padding_bottom": 16
          }
        }
      },
      "block_order": [
        "heading_KfRRxy",
        "text_yFYiAe"
      ],
      "name": "Image with text",
      "settings": {
        "image_1": "shopify://shop_images/WhatsApp_Image_2026-03-18_at_11.15.12_AM.jpg",
        "image_width": "one-half",
        "text_alignment": "text-left",
        "layout": "",
        "width": "wrapper--full",
        "height": "screen-height-three-quarters",
        "mobile_height": "screen-height-one-half--mobile",
        "reverse_blocks": false,
        "color_scheme": "",
        "padding_top": 0,
        "padding_bottom": 20,
        "show_placeholder": true
      }
    },
    "section_multicolumn_d4Wkyq": {
      "type": "section-multicolumn",
      "blocks": {
        "icon_NhE7TV": {
          "type": "icon",
          "settings": {
            "column_width": 33,
            "icon_name": "icon-trophy",
            "icon_size": 20,
            "icon_alignment": "icon--top",
            "icon_color": "",
            "title": "Full-Grain Leather",
            "heading_font_size": "heading-small",
            "text": "<p>Sourced from premium tanneries. Develops a natural patina over time \u2014 the more it's worn, the better it looks</p>",
            "text_font_size": "body-medium",
            "heading_tag": "automatic"
          }
        },
        "icon_XnCMpY": {
          "type": "icon",
          "settings": {
            "column_width": 33,
            "icon_name": "icon-droplet",
            "icon_size": 20,
            "icon_alignment": "icon--top",
            "icon_color": "",
            "title": "Signature Colourways",
            "heading_font_size": "heading-small",
            "text": "<p>Each collar is named after a shade, not just a colour. Every colourway is designed to complement your dog's coat.</p>",
            "text_font_size": "body-medium",
            "heading_tag": "automatic"
          }
        },
        "icon_gxwNiF": {
          "type": "icon",
          "settings": {
            "column_width": 33,
            "icon_name": "icon-shield",
            "icon_size": 20,
            "icon_alignment": "icon--top",
            "icon_color": "",
            "title": "Solid Brass Hardware",
            "heading_font_size": "heading-small",
            "text": "<p>Brass D-ring and centre-bar buckle. Built to last, with a warm patina that ages alongside the leather.</p>",
            "text_font_size": "body-medium",
            "heading_tag": "automatic"
          }
        }
      },
      "block_order": [
        "icon_NhE7TV",
        "icon_XnCMpY",
        "icon_gxwNiF"
      ],
      "name": "Multi column",
      "settings": {
        "title": "",
        "heading_font_size": "heading-medium",
        "description": "",
        "align_heading": "text-left",
        "align_text": "text-left",
        "width": "wrapper--full-padded",
        "align_columns": "flex-align-top",
        "layout_mobile": "slider",
        "color_scheme": "scheme-4110170d-bf2f-4319-8d1c-dfb045cbf076",
        "padding_top": 50,
        "padding_bottom": 50,
        "heading_tag": "automatic"
      }
    },
    "shipping": {
      "type": "section-accordion",
      "blocks": {
        "shipping-0": {
          "type": "icon",
          "settings": {
            "icon_name": "icon-green-shipment",
            "icon_size": 20,
            "icon_color": "",
            "title": "International Shipping",
            "heading_font_size": "heading-x-small",
            "icon_alignment": "left",
            "text": "<p>We are happy to announce we officially ship internationally! All orders are dispatched from our US warehouse within 2 - 3 business days.</p>",
            "text_alignment": "text-left"
          }
        },
        "shipping-1": {
          "type": "icon",
          "settings": {
            "icon_name": "icon-location",
            "icon_size": 20,
            "icon_color": "",
            "title": "30-Day Returns",
            "heading_font_size": "heading-x-small",
            "icon_alignment": "left",
            "text": "<p>We want you \u2014 and your dog \u2014 to love every PAWD piece. If something isn't right, return it within 30 days of delivery for a full refund or exchange. Items must be unused and in original condition</p>",
            "text_alignment": "text-left"
          }
        },
        "shipping-2": {
          "type": "icon",
          "settings": {
            "icon_name": "icon-chat",
            "icon_size": 20,
            "icon_color": "",
            "title": "Engraving & Lead Time",
            "heading_font_size": "heading-x-small",
            "icon_alignment": "left",
            "text": "<p>Personalised collars are hand-engraved to order. Please allow an additional 3\u20135 business days for engraving before dispatch. We'll confirm your engraving details by email before we begin.</p>",
            "text_alignment": "text-left"
          }
        }
      },
      "block_order": [
        "shipping-0",
        "shipping-1",
        "shipping-2"
      ],
      "settings": {
        "default_open": false,
        "title": "Shipping  & Returns",
        "heading_font_size": "heading-x-small",
        "show_icon": false,
        "icon_name": "icon-award",
        "icon_size": 20,
        "width": "wrapper",
        "color_scheme": "scheme-8a8a0884-d182-4e82-9721-b5dd023210e6",
        "icon_color": "",
        "padding_top": 20,
        "padding_bottom": 0
      }
    },
    "1773140064d83b4e57": {
      "type": "apps",
      "blocks": {
        "junip_junip_product_review_xzCB6k": {
          "type": "shopify://apps/junip/blocks/junip-product-review/dc14f5a8-ed15-41b1-ad08-cfba23f9789b",
          "settings": {
            "product": "{{product}}",
            "title": "",
            "alignment": "",
            "sortOrder": "mostRecent"
          }
        }
      },
      "block_order": [
        "junip_junip_product_review_xzCB6k"
      ],
      "settings": {
        "include_margins": false
      }
    },
    "related": {
      "type": "related",
      "blocks": {
        "related": {
          "type": "related",
          "settings": {
            "product_recommendations_heading": "Related products"
          }
        },
        "recent": {
          "type": "recent",
          "settings": {
            "product_recently_heading": "Recently viewed"
          }
        }
      },
      "block_order": [
        "related",
        "recent"
      ],
      "settings": {
        "enable_tabs": true,
        "heading_alignment": "text-center",
        "heading_font_size": "heading-small",
        "limit": 4,
        "layout_desktop": "slider",
        "grid": 4,
        "rows": 3,
        "layout_mobile": "slider",
        "color_scheme": "scheme-8a8a0884-d182-4e82-9721-b5dd023210e6",
        "padding_top": 60,
        "padding_bottom": 60
      }
    }
  },
  "order": [
    "section_divider_WfYLrb",
    "main",
    "section_accordion_NMDgJD",
    "section_hero_Cz9YYe",
    "section_double_7bAatG",
    "section_multicolumn_d4Wkyq",
    "shipping",
    "1773140064d83b4e57",
    "related"
  ]
}
